[
  {
    "a":2000,
    "dat":18,
    "fill": "blue"
  },
  {
    "a":2001,
    "dat":10,
    "fill": "blue"
  },
  {
    "a":2002,
    "dat":20,
    "fill": "blue"
  },
  {
    "a":2003,
    "dat":22,
    "fill": "blue"
  },
  {
    "a":2004,
    "dat":53,
    "fill": "blue"
  },
  {
    "a":2005,
    "dat":77,
    "fill": "blue"
  },
  {
    "a":2006,
    "dat":25,
    "fill": "blue"
  },
  {
    "a":2007,
    "dat":29,
    "fill": "blue"
  },
  {
    "a":2008,
    "dat":32,
    "fill": "blue"
  },
  {
    "a":2009,
    "dat":8,
    "fill": "blue"
  },
  {
    "a":2010,
    "dat":12,
    "fill": "blue"
  },
  {
    "a":2011,
    "dat":40,
    "fill": "blue"
  },
  {
    "a":2012,
    "dat":55,
    "fill": "blue"
  },
  {
    "a":2013,
    "dat":34,
    "fill": "blue"
  },
  {
    "a":2014,
    "dat":44,
    "fill": "blue"
  },
  {
    "a":2015,
    "dat":5,
    "fill": "blue"
  },
  {
    "a":2016,
    "dat":60,
    "fill": "blue"
  },
  {
    "a":2017,
    "dat":70,
    "fill": "blue"
  },
  {
    "a":2018,
    "dat":80,
    "fill": "blue"
  },
  {
    "a":2019,
    "dat":100,
    "fill": "blue"
  },
  {
    "a":2020,
    "dat":58,
    "fill": "blue"
  },
  {
    "a":2021,
    "dat":10,
    "fill": "blue"
  },
  {
    "a":2022,
    "dat":98,
    "fill": "blue"
  },
  {
    "a":2023,
    "dat":112,
    "fill": "blue"
  }
]